CopaData/__init__.py
CopaData/pyZAN.py
copadata-15.0.0.dist-info/licenses/LICENSE
copadata-15.0.0.dist-info/METADATA
copadata-15.0.0.dist-info/WHEEL
copadata-15.0.0.dist-info/top_level.txt
copadata-15.0.0.dist-info/RECORD
