Metadata-Version: 2.4
Name: CopaData
Version: 15.0.0
Summary: Read metadata and online data from Report Engine Server
Home-page: https://www.copadata.com
Author: COPA-DATA
Author-email: development@copadata.com
Classifier: Programming Language :: Python :: 3
Classifier: License :: OSI Approved :: MIT License
Classifier: Operating System :: Microsoft :: Windows
Requires-Python: >=3.7
License-File: LICENSE
Dynamic: author
Dynamic: author-email
Dynamic: classifier
Dynamic: description
Dynamic: description-content-type
Dynamic: home-page
Dynamic: license-file
Dynamic: requires-python
Dynamic: summary
